__init__.py
slackify_markdown/__init__.py
slackify_markdown/service.py
slackify_markdown/slackify.py
slackify_markdown/utils.py
slackify_markdown-0.1.4.dist-info/LICENSE
slackify_markdown-0.1.4.dist-info/METADATA
slackify_markdown-0.1.4.dist-info/WHEEL
slackify_markdown-0.1.4.dist-info/top_level.txt
slackify_markdown-0.1.4.dist-info/RECORD
