Metadata-Version: 2.2
Name: slackify_markdown
Version: 0.1.4
Summary: Convert markdown to Slack-compatible formatting
Author-email: Manthan Surkar <manthan1674@gmail.com>
License: MIT License
Project-URL: Homepage, https://github.com/thesmallstar/slackify-markdown-python
Project-URL: Bug Tracker, https://github.com/thesmallstar/slackify-markdown-python/issues
Project-URL: Documentation, https://github.com/thesmallstar/slackify-markdown-python#readme
Keywords: slack,markdown,mrkdwn,converter,formatting,text
Classifier: Programming Language :: Python :: 3.8
Classifier: Programming Language :: Python :: 3.9
Classifier: Programming Language :: Python :: 3.10
Classifier: Programming Language :: Python :: 3.11
Classifier: Programming Language :: Python :: 3.12
Classifier: Programming Language :: Python :: 3.13
Classifier: License :: OSI Approved :: MIT License
Classifier: Operating System :: OS Independent
Classifier: Intended Audience :: Developers
Classifier: Topic :: Communications :: Chat
Requires-Python: >=3.8
License-File: LICENSE
Provides-Extra: dev
Requires-Dist: pytest>=7.0.0; extra == "dev"
